sciai/__init__.py
sciai/build_info.txt
sciai/setup.py
sciai/version.py
sciai/architecture/__init__.py
sciai/architecture/activation.py
sciai/architecture/basic_block.py
sciai/architecture/neural_operators/__init__.py
sciai/architecture/neural_operators/dft.py
sciai/architecture/neural_operators/fno1d.py
sciai/architecture/neural_operators/fno2d.py
sciai/architecture/neural_operators/fno3d.py
sciai/architecture/neural_operators/kno1d.py
sciai/architecture/neural_operators/kno2d.py
sciai/architecture/neural_operators/m2k.py
sciai/architecture/neural_operators/pdenet.py
sciai/architecture/transformer/__init__.py
sciai/architecture/transformer/layer.py
sciai/architecture/transformer/vit.py
sciai/common/__init__.py
sciai/common/dataset.py
sciai/common/initializer.py
sciai/common/optimizer.py
sciai/common/train_cell.py
sciai/context/__init__.py
sciai/context/context.py
sciai/model/__init__.py
sciai/model/auto_mindsponge.py
sciai/model/auto_model.py
sciai/model/model_status.yaml
sciai/model/package_version.yaml
sciai/model/auq_pinns/__init__.py
sciai/model/auq_pinns/config.yaml
sciai/model/auq_pinns/eval.py
sciai/model/auq_pinns/train.py
sciai/model/auq_pinns/src/__init__.py
sciai/model/auq_pinns/src/network.py
sciai/model/auq_pinns/src/plot.py
sciai/model/auq_pinns/src/process.py
sciai/model/cpinns/__init__.py
sciai/model/cpinns/config.yaml
sciai/model/cpinns/eval.py
sciai/model/cpinns/train.py
sciai/model/cpinns/src/__init__.py
sciai/model/cpinns/src/network.py
sciai/model/cpinns/src/plot.py
sciai/model/cpinns/src/process.py
sciai/model/deep_hpms/__init__.py
sciai/model/deep_hpms/config.yaml
sciai/model/deep_hpms/eval.py
sciai/model/deep_hpms/train.py
sciai/model/deep_hpms/src/__init__.py
sciai/model/deep_hpms/src/network_burgers_different.py
sciai/model/deep_hpms/src/network_common.py
sciai/model/deep_hpms/src/network_kdv_same.py
sciai/model/deep_hpms/src/plot.py
sciai/model/deep_hpms/src/process.py
sciai/model/deep_ritz/__init__.py
sciai/model/deep_ritz/config.yaml
sciai-0.1.0.dist-info/METADATA
sciai-0.1.0.dist-info/WHEEL
sciai-0.1.0.dist-info/top_level.txt
sciai-0.1.0.dist-info/RECORD
